shiftregisterandmultiplier/shiftregisterandmultiplier.srcs/sources_1/new/adder.v
`timescale 1ns / 1ps
//////////////////////////////////////////////////////////////////////////////////
// Company: 
// Engineer: 
// 
// Create Date: 04/06/2024 12:58:03 PM
// Design Name: 
// Module Name: adder
// Project Name: 
// Target Devices: 
// Tool Versions: 
// Description: 
// 
// Dependencies: 
// 
// Revision:
// Revision 0.01 - File Created
// Additional Comments:
// 
//////////////////////////////////////////////////////////////////////////////////

module adder(
    input [5:0] A, // 6-bit input A
    input [5:0] B, // 6-bit input B
    input Cin,     // Carry input
    output [5:0] Sum, // 6-bit sum output
    output Cout    // Carry output
);

// Generate (G) and Propagate (P) signals
wire [5:0] G;
wire [5:0] P;
wire [6:0] C; // Intermediate carries, C[0] is Cin

assign C[0] = Cin;

// Calculating Generate and Propagate for each bit
genvar i;
generate
    for (i = 0; i < 6; i = i + 1) begin: loop
        assign G[i] = A[i] & B[i]; // Generate
        assign P[i] = A[i] ^ B[i]; // Propagate
        assign C[i+1] = G[i] | (P[i] & C[i]); // Carry for next bit
    end
endgenerate

// Sum and Carry out calculation
assign Sum = P ^ C[5:0]; // Sum calculation
assign Cout = C[6]; // Final carry out

endmodule

shiftregisterandmultiplier/shiftregisterandmultiplier.srcs/sources_1/new/shifter.v
`timescale 1ns / 1ps
//////////////////////////////////////////////////////////////////////////////////
// Company: 
// Engineer: 
// 
// Create Date: 04/13/2024 01:56:31 AM
// Design Name: 
// Module Name: shifter
// Project Name: 
// Target Devices: 
// Tool Versions: 
// Description: 
// 
// Dependencies: 
// 
// Revision:
// Revision 0.01 - File Created
// Additional Comments:
// 
//////////////////////////////////////////////////////////////////////////////////

module shifter(
    input clk,
    input reset,
    input [3:0] A,
    input [1:0] selection,
    output reg [5:0] shifted  // Corrected to use 6-bit output
);
    reg [5:0] register;  // Corrected internal register to 6 bits

    always @(posedge clk or posedge reset) begin
        if (reset)
            register <= 6'b000000;
        else begin
            case(selection)
                2'b00: register <= {2'b00, A};  // No shift, load A into the lower bits with 2-bit padding
                2'b01: register <= {1'b0, A, 1'b0};  // Shift left by 1
                2'b10: register <= {3'b000, A[3:1]};  // Corrected: Shift right by 1, MSB lost, LSB padded with 0
                2'b11: register <= {A, 2'b00};  // Shift left by 2
                default: register <= 6'b000000;
            endcase
        end
    end

    always @(register)
        shifted <= register;
endmodule

shiftregisterandmultiplier/shiftregisterandmultiplier.srcs/sources_1/new/multiplier.v
`timescale 1ns / 1ps
//////////////////////////////////////////////////////////////////////////////////
// Company: 
// Engineer: 
// 
// Create Date: 04/06/2024 12:42:42 PM
// Design Name: 
// Module Name: multiplier
// Project Name: 
// Target Devices: 
// Tool Versions: 
// Description: 
// 
// Dependencies: 
// 
// Revision:
// Revision 0.01 - File Created
// Additional Comments:
// 
//////////////////////////////////////////////////////////////////////////////////

module multiplier(
    input clk,
    input reset,
    input [3:0] inp,
    output [6:0] sum  // Updated to 7-bit output
);
    wire [5:0] nstar2_extended; 
    wire [5:0] nstar4_extended;
    wire [5:0] intermediate_sum; // This is a temporary 6-bit sum from the adder
    wire carry_out;  // Temporary carry out

    // Instantiate shifter modules with corrected bit widths
    shifter m2(.clk(clk), .reset(reset), .A(inp), .selection(2'b01), .shifted(nstar2_extended));
    shifter m4(.clk(clk), .reset(reset), .A(inp), .selection(2'b11), .shifted(nstar4_extended));

    // Use an adder to sum the outputs of the shift registers
    adder a1(
        .A(nstar2_extended), 
        .B(nstar4_extended), 
        .Cin(0), 
        .Sum(intermediate_sum), 
        .Cout(carry_out)
    );

    // Combine the sum and the carry out to form a 7-bit output
    assign sum = {carry_out, intermediate_sum};  // Prepend carry_out to intermediate_sum to form 7 bits

    // Print statements to observe values on every positive edge of the clock
    always @(posedge clk) begin
        if (!reset) begin  // Only display values when not in reset
            $display("Time: %t, Input: %b", $time, inp);
            $display("Shifted *2 (nstar2_extended): %b", nstar2_extended);
            $display("Shifted *4 (nstar4_extended): %b", nstar4_extended);
            $display("7-bit Sum: %b", sum);
        end
    end

    // Also print on reset to observe reset state
    always @(posedge reset) begin
        $display("Reset activated at time: %t", $time);
        $display("All outputs and intermediates are reset to zero or default states.");
    end
endmodule

shiftregisterandmultiplier/shiftregisterandmultiplier.srcs/sim_2/new/testbench.v
`timescale 1ns / 1ps
//////////////////////////////////////////////////////////////////////////////////
// Company: 
// Engineer: 
// 
// Create Date: 04/13/2024 02:01:42 AM
// Design Name: 
// Module Name: testbench
// Project Name: 
// Target Devices: 
// Tool Versions: 
// Description: 
// 
// Dependencies: 
// 
// Revision:
// Revision 0.01 - File Created
// Additional Comments:
// 
//////////////////////////////////////////////////////////////////////////////////


`timescale 1ns / 1ps

module tb_multiplier();

    reg clk;
    reg reset;
    reg [3:0] inp;
    wire [6:0] sum;  // Adjusted for 7-bit output

    // Instantiate the modified multiplier
    multiplier uut(
        .clk(clk),
        .reset(reset),
        .inp(inp),
        .sum(sum)  // Only sum is needed, no Cout
    );

    // Clock generation
    always #10 clk = ~clk;  // Generate a clock with a period of 20 ns

    // Initial block to provide test stimuli
    initial begin
        // Initialize Inputs
        clk = 0;
        reset = 1;
        inp = 4'b0000;

        // Reset the design
        #30 reset = 0;

        // Sequentially test various input values
        inp = 4'b0001; #20;
        inp = 4'b0010; #20;
        inp = 4'b0011; #20;
        inp = 4'b0100; #20;
        inp = 4'b0101; #20;
        inp = 4'b0110; #20;
        inp = 4'b0111; #20;
        inp = 4'b1000; #20;
        inp = 4'b1001; #20;
        inp = 4'b1010; #20;
        inp = 4'b1011; #20;
        inp = 4'b1100; #20;
        inp = 4'b1101; #20;
        inp = 4'b1110; #20;
        inp = 4'b1111; #20;

        // Reassert reset to test reset functionality
        reset = 1; #20;
        reset = 0; #20;

        // Finish simulation
        $finish;
    end

    // Optional: Output waveforms for analysis
    initial begin
        $dumpfile("multiplier_tb.vcd");
        $dumpvars(0, tb_multiplier);
    end

    // Monitoring outputs
    initial begin
        $monitor("Time = %t, Input = %b, 7-bit Sum = %b", $time, inp, sum);
    end

endmodule

shiftregisterandmultiplier/shiftregisterandmultiplier.sim/sim_2/behav/xsim/multiplier_tb.vcd
$date
   Sun Apr 14 22:23:29 2024
$end

$version
  2023.2
  $dumpfile ("multiplier_tb.vcd") 
$end

$timescale
  1ps
$end

$scope module tb_multiplier $end
$var reg 1 ! clk $end
$var reg 1 " reset $end
$var reg 4 # inp [3:0] $end
$var wire 7 $ sum [6:0] $end
$scope module uut $end
$var wire 1 % clk $end
$var wire 1 & reset $end
$var wire 4 ' inp [3:0] $end
$var wire 7 $ sum [6:0] $end
$var wire 6 ( nstar2_extended [5:0] $end
$var wire 6 ) nstar4_extended [5:0] $end
$var wire 6 * intermediate_sum [5:0] $end
$var wire 1 + carry_out $end
$scope module m2 $end
$var wire 1 % clk $end
$var wire 1 & reset $end
$var wire 4 ' A [3:0] $end
$var wire 2 , selection [1:0] $end
$var reg 6 - shifted [5:0] $end
$var reg 6 . register [5:0] $end
$upscope $end
$scope module m4 $end
$var wire 1 % clk $end
$var wire 1 & reset $end
$var wire 4 ' A [3:0] $end
$var wire 2 / selection [1:0] $end
$var reg 6 0 shifted [5:0] $end
$var reg 6 1 register [5:0] $end
$upscope $end
$scope module a1 $end
$var wire 6 ( A [5:0] $end
$var wire 6 ) B [5:0] $end
$var wire 1 2 Cin $end
$var wire 6 * Sum [5:0] $end
$var wire 1 + Cout $end
$var wire 6 3 G [5:0] $end
$var wire 6 4 P [5:0] $end
$var wire 7 5 C [6:0] $end
$upscope $end
$upscope $end
$upscope $end
$enddefinitions $end

#0
$dumpvars
0!
1"
b0 #
b0 $
0%
1&
b0 '
b0 (
b0 )
b0 *
0+
b1 ,
b0 -
b0 .
b11 /
b0 0
b0 1
02
b0 3
b0 4
b0 5
$end

#10000
1!
1%

#20000
0!
0%

#30000
1!
0"
b1 #
b110 $
1%
0&
b1 '
b10 (
b100 )
b110 *
b10 -
b10 .
b100 0
b100 1
b110 4

#40000
0!
0%

#50000
1!
b10 #
b1100 $
1%
b10 '
b100 (
b1000 )
b1100 *
b100 -
b100 .
b1000 0
b1000 1
b1100 4

#60000
0!
0%

#70000
1!
b11 #
b10010 $
1%
b11 '
b110 (
b1100 )
b10010 *
b110 -
b110 .
b1100 0
b1100 1
b100 3
b1010 4
b11000 5

#80000
0!
0%

#90000
1!
b100 #
b11000 $
1%
b100 '
b1000 (
b10000 )
b11000 *
b1000 -
b1000 .
b10000 0
b10000 1
b0 3
b11000 4
b0 5

#100000
0!
0%

#110000
1!
b101 #
b11110 $
1%
b101 '
b1010 (
b10100 )
b11110 *
b1010 -
b1010 .
b10100 0
b10100 1
b11110 4

#120000
0!
0%

#130000
1!
b110 #
b100100 $
1%
b110 '
b1100 (
b11000 )
b100100 *
b1100 -
b1100 .
b11000 0
b11000 1
b1000 3
b10100 4
b110000 5

#140000
0!
0%

#150000
1!
b111 #
b101010 $
1%
b111 '
b1110 (
b11100 )
b101010 *
b1110 -
b1110 .
b11100 0
b11100 1
b1100 3
b10010 4
b111000 5

#160000
0!
0%

#170000
1!
b1000 #
b110000 $
1%
b1000 '
b10000 (
b100000 )
b110000 *
0+
b10000 -
b10000 .
b100000 0
b100000 1
b0 3
b110000 4
b0 5

#180000
0!
0%

#190000
1!
b1001 #
b110110 $
1%
b1001 '
b10010 (
b100100 )
b110110 *
b10010 -
b10010 .
b100100 0
b100100 1
b110110 4

#200000
0!
0%

#210000
1!
b1010 #
b111100 $
1%
b1010 '
b10100 (
b101000 )
b111100 *
b10100 -
b10100 .
b101000 0
b101000 1
b111100 4

#220000
0!
0%

#230000
1!
b1011 #
b1000010 $
1%
b1011 '
b10110 (
b101100 )
b10 *
1+
b10110 -
b10110 .
b101100 0
b101100 1
b100 3
b111010 4
b1111000 5

#240000
0!
0%

#250000
1!
b1100 #
b1001000 $
1%
b1100 '
b11000 (
b110000 )
b1000 *
b11000 -
b11000 .
b110000 0
b110000 1
b10000 3
b101000 4
b1100000 5

#260000
0!
0%

#270000
1!
b1101 #
b1001110 $
1%
b1101 '
b11010 (
b110100 )
b1110 *
b11010 -
b11010 .
b110100 0
b110100 1
b101110 4

#280000
0!
0%

#290000
1!
b1110 #
b1010100 $
1%
b1110 '
b11100 (
b111000 )
b10100 *
b11100 -
b11100 .
b111000 0
b111000 1
b11000 3
b100100 4
b1110000 5

#300000
0!
0%

#310000
1!
b1111 #
b1011010 $
1%
b1111 '
b11110 (
b111100 )
b11010 *
b11110 -
b11110 .
b111100 0
b111100 1
b11100 3
b100010 4
b1111000 5
